cnt/__init__.py
cnt/data/__init__.py
cnt/data/dataset.py
cnt/generator/__init__.py
cnt/generator/generator.py
cnt/robustness/__init__.py
cnt/robustness/network_attack.py
cnt/robustness/simulated_attack.py
cnt/robustness_optimization/__init__.py
cnt/robustness_optimization/GA/__init__.py
cnt/robustness_optimization/GA/cross_over.py
cnt/robustness_optimization/GA/individual.py
cnt/robustness_optimization/GA/population.py
cnt/robustness_optimization/GA/utils.py
cnt/robustness_prediction/__init__.py
cnt/robustness_prediction/models/__init__.py
cnt/robustness_prediction/models/keras/__init__.py
cnt/robustness_prediction/models/keras/parameters.py
cnt/robustness_prediction/models/keras/save_lfr_tensors.py
cnt/robustness_prediction/models/keras/test_cnn.py
cnt/robustness_prediction/models/keras/train_cnn.py
cnt/robustness_prediction/models/keras/utils_cnn.py
cnt/robustness_prediction/models/keras/CNN_LFR/CNN_LFR.py
cnt/robustness_prediction/models/keras/CNN_LFR/__init__.py
cnt/robustness_prediction/models/keras/CNN_LFR/embedding.py
cnt/robustness_prediction/models/keras/CNN_LFR/receptive_field.py
cnt/robustness_prediction/models/keras/CNN_LFR/util_pscn.py
cnt/robustness_prediction/models/keras/CNN_RP/CNN_RP.py
cnt/robustness_prediction/models/keras/CNN_RP/__init__.py
cnt/robustness_prediction/models/keras/CNN_SPP/CNN_SPP.py
cnt/robustness_prediction/models/keras/CNN_SPP/SpatialPyramidPooling.py
cnt/robustness_prediction/models/keras/CNN_SPP/__init__.py
cnt/robustness_prediction/models/troch/__init__.py
cnt/robustness_prediction/models/troch/run_demo.py
cnt/robustness_prediction/models/troch/save_lfr_tensors.py
cnt/robustness_prediction/models/troch/tool_functions.py
cnt/robustness_prediction/models/troch/train_test.py
cnt/robustness_prediction/models/troch/utils_cnn.py
cnt/robustness_prediction/models/troch/utils_gnn.py
cnt/robustness_prediction/models/troch/CNN_LFR/CNN_LFR.py
cnt/robustness_prediction/models/troch/CNN_LFR/__init__.py
complex_network_tools-0.2.4.dist-info/LICENSE
complex_network_tools-0.2.4.dist-info/METADATA
complex_network_tools-0.2.4.dist-info/WHEEL
complex_network_tools-0.2.4.dist-info/top_level.txt
complex_network_tools-0.2.4.dist-info/RECORD
