Metadata-Version: 2.1
Name: complex-network-tools
Version: 0.2.4
Summary: A Python package for generating, learning, and analysis of complex networks.
Home-page: https://github.com/chengpei-wu/ComplexNetwork
Author: Chengpei Wu
Author-email: chengpei.wu@hotmail.com
License: MIT
Classifier: License :: OSI Approved :: MIT License
Classifier: Programming Language :: Python
Classifier: Programming Language :: Python :: 3
Classifier: Programming Language :: Python :: 3.6
Classifier: Programming Language :: Python :: Implementation :: CPython
Classifier: Programming Language :: Python :: Implementation :: PyPy
Requires-Python: >=3.6.0
License-File: LICENSE
Requires-Dist: scipy
Requires-Dist: networkx
Requires-Dist: numpy
Requires-Dist: dgl
Requires-Dist: torch
Requires-Dist: pytest
